[{"Type":"9","TextS":"tick off task;buyer;s to buyer","TextC":"","InitiateParty":"Buy","Communication":"5","Stage":"D","vtextC":false,"vBuyerToSolicitor":false,"vSellertoSolicitor":false,"vSolicitorToBuyer":true,"vSolicitorToSeller":false,"vSSolicitorToBSolicitor":false,"vBSolicitorToSSolicitor":false},{"Type":"8","TextS":"inform;buy;s to buyer","TextC":"","InitiateParty":"Buy","Communication":"5","Stage":"C","vtextC":false,"vBuyerToSolicitor":false,"vSellertoSolicitor":false,"vSolicitorToBuyer":true,"vSolicitorToSeller":false,"vSSolicitorToBSolicitor":false,"vBSolicitorToSSolicitor":false},{"Type":"1","TextS":"","TextC":"","InitiateParty":"Buy","Communication":"5","Stage":"A","vtextC":true,"vBuyerToSolicitor":true,"vSellertoSolicitor":false,"vSolicitorToBuyer":true,"vSolicitorToSeller":false,"vSSolicitorToBSolicitor":false,"vBSolicitorToSSolicitor":true},{"Type":"6","TextS":"advice; buy; s to buyer","TextC":"file from solicitor","InitiateParty":"Buy","Communication":"1","Stage":"B","vtextC":false,"vBuyerToSolicitor":false,"vSellertoSolicitor":false,"vSolicitorToBuyer":true,"vSolicitorToSeller":false,"vSSolicitorToBSolicitor":false,"vBSolicitorToSSolicitor":false}]